postgresify.py
django_heroku_postgresify-0.4.1.dist-info/METADATA
django_heroku_postgresify-0.4.1.dist-info/WHEEL
django_heroku_postgresify-0.4.1.dist-info/top_level.txt
django_heroku_postgresify-0.4.1.dist-info/RECORD
