Metadata-Version: 2.1
Name: django-heroku-postgresify
Version: 0.4.1
Summary: Automatic Django database configuration on Heroku.
Home-page: https://github.com/rdegges/django-heroku-postgresify
Author: Randall Degges
Author-email: rdegges@gmail.com
License: UNLICENSE
Keywords: django heroku cloud postgresql postgres db database awesome epic
Platform: UNKNOWN
